dj_brevo/__init__.py
dj_brevo/admin.py
dj_brevo/apps.py
dj_brevo/exceptions.py
dj_brevo/py.typed
dj_brevo/settings.py
dj_brevo/backends/__init__.py
dj_brevo/backends/email.py
dj_brevo/models/__init__.py
dj_brevo/models/attributes.py
dj_brevo/models/base.py
dj_brevo/models/contacts.py
dj_brevo/models/lists.py
dj_brevo/services/__init__.py
dj_brevo/services/client.py
dj_brevo/signals/__init__.py
dj_brevo/signals/handlers.py
dj_brevo-0.3.2.dist-info/METADATA
dj_brevo-0.3.2.dist-info/WHEEL
dj_brevo-0.3.2.dist-info/licenses/LICENSE
dj_brevo-0.3.2.dist-info/RECORD
