Metadata-Version: 2.4
Name: dj-brevo
Version: 0.3.2
Summary: Django + Brevo for transactional emails and customer journey automations.
Project-URL: Homepage, https://github.com/dmckim1977/dj-brevo
Project-URL: Repository, https://github.com/dmckim1977/dj-brevo
Project-URL: Issues, https://github.com/dmckim1977/dj-brevo/issues
Author-email: David McKim <davidmckim@gmail.com>
License-Expression: MIT
License-File: LICENSE
Keywords: brevo,django,email,marketing,sendinblue,transactional
Classifier: Development Status :: 3 - Alpha
Classifier: Environment :: Web Environment
Classifier: Framework :: Django
Classifier: Framework :: Django :: 5.0
Classifier: Framework :: Django :: 5.1
Classifier: Intended Audience :: Developers
Classifier: License :: OSI Approved :: MIT License
Classifier: Operating System :: OS Independent
Classifier: Programming Language :: Python :: 3
Classifier: Programming Language :: Python :: 3.12
Classifier: Programming Language :: Python :: 3.13
Requires-Python: >=3.10
Requires-Dist: django>=5.0
Requires-Dist: httpx>=0.27
